startic/__init__.py
startic/main.py
startic/.system/imports.py
startic/.system/index.py
startic/.system/modules/-placeholder
startic/.system/sources/clight.json
startic/.system/sources/logo.ico
startic/.system/sources/sitemap.xml
startic/frame/.gitignore
startic/frame/index.html
startic/frame/pages.yml
startic/frame/robots.txt
startic/frame/assets/logo.png
startic/frame/assets/sitemap.xml
startic/frame/assets/startic.json
startic/frame/parts/.html
startic/frame/parts/author.html
startic/frame/parts/details.html
startic/frame/parts/intro.html
startic/frame/parts/links.html
startic/frame/social/linkedin.html
startic/frame/social/mail.html
startic/frame/social/x.html
startic-1.1.5.dist-info/licenses/LICENSE
startic-1.1.5.dist-info/METADATA
startic-1.1.5.dist-info/WHEEL
startic-1.1.5.dist-info/entry_points.txt
startic-1.1.5.dist-info/top_level.txt
startic-1.1.5.dist-info/RECORD
