Metadata-Version: 2.4
Name: startic
Version: 1.1.5
Summary: Startic is a Python CLI tool for quickly building static webpages, allowing you to start publishing lightweight templates with ease
Home-page: https://github.com/IG-onGit/Startic
Author: Irakli Gzirishvili
Author-email: gziraklirex@gmail.com
Classifier: Programming Language :: Python :: 3
Classifier: License :: OSI Approved :: MIT License
Classifier: Operating System :: OS Independent
License-File: LICENSE
Requires-Dist: clight
Dynamic: author
Dynamic: author-email
Dynamic: classifier
Dynamic: description
Dynamic: description-content-type
Dynamic: home-page
Dynamic: license-file
Dynamic: requires-dist
Dynamic: summary
